nyt_recipe/__init__.py
nyt_recipe/main.py
nyt_recipe/output.py
nyt_recipe/recipe.py
nyt_recipe-1.2.0.dist-info/LICENSE
nyt_recipe-1.2.0.dist-info/METADATA
nyt_recipe-1.2.0.dist-info/WHEEL
nyt_recipe-1.2.0.dist-info/entry_points.txt
nyt_recipe-1.2.0.dist-info/RECORD
