Metadata-Version: 2.1
Name: nyt_recipe
Version: 1.2.0
Summary: Downloads recipes from the NYT Cooking website and converts them into an Apple Notes-compatible format
Home-page: https://github.com/ianbrault/nyt_recipe
License: MIT
Author: Ian Brault
Author-email: ian@brault.dev
Requires-Python: >=3.9,<4.0
Classifier: License :: OSI Approved :: MIT License
Classifier: Programming Language :: Python :: 3
Classifier: Programming Language :: Python :: 3.9
Classifier: Programming Language :: Python :: 3.10
Classifier: Programming Language :: Python :: 3.11
Classifier: Programming Language :: Python :: 3.12
Requires-Dist: beautifulsoup4 (>=4.12,<5.0)
Requires-Dist: requests (>=2.31,<3.0)
Project-URL: Repository, https://github.com/ianbrault/nyt_recipe
